envargs/__init__.py
envargs/envargs.py
envargs/errors.py
envarguments-1.0.1.dist-info/METADATA
envarguments-1.0.1.dist-info/WHEEL
envarguments-1.0.1.dist-info/licenses/LICENSE
envarguments-1.0.1.dist-info/RECORD
