Metadata-Version: 2.1
Name: envarguments
Version: 1.0.1
Summary: Utility to specify which environment variable shall be used as arguments for a program.
Project-URL: Homepage, https://github.com/maansthoernvik/envargs
Project-URL: Bug Tracker, https://github.com/maansthoernvik/envargs/issues
Author-email: Måns Thörnvik <thornvik.mans@gmail.com>
License-File: LICENSE
Classifier: License :: OSI Approved :: MIT License
Classifier: Operating System :: OS Independent
Classifier: Programming Language :: Python :: 3
Requires-Python: >=3.7
